{
  "fileTitle": "data",
  "summaryFileData": {
    "totals": [
      {
        "summaryTotalId": "total-1",
        "total_cust_a": {
          "val": 286
        },
        "total_percent_cust_a": {
          "val": 0.02
        },
        "total_percent_cust_active": {
          "val": 99.98
        },
        "total_cust_s": 2243204,
        "total_outages": 86
      }
    ],
    "date_generated": "2024-04-04T19:04:26.831Z",
    "overwritten_ca": false,
    "overwritten_etr": false,
    "page_mode": {
      "mode": "BLUESKY",
      "redirectURL": "",
      "pausePublish": false
    }
  }
}