{
  "fileTitle": "data",
  "summaryFileData": {
    "totals": [
      {
        "summaryTotalId": "total-1",
        "total_cust_a": {
          "val": 1196
        },
        "total_percent_cust_a": {
          "val": 0.05
        },
        "total_percent_cust_active": {
          "val": 99.95
        },
        "total_cust_s": 2456305,
        "total_outages": 140
      }
    ],
    "date_generated": "2023-09-29T15:15:45.924Z",
    "overwritten_ca": false,
    "overwritten_etr": false,
    "page_mode": {
      "mode": "BLUESKY",
      "redirectURL": "",
      "pausePublish": false
    }
  }
}