{
  "fileTitle": "data",
  "summaryFileData": {
    "totals": [
      {
        "summaryTotalId": "total-1",
        "total_cust_a": {
          "val": 1148
        },
        "total_percent_cust_a": {
          "val": 0.06
        },
        "total_percent_cust_active": {
          "val": 99.94
        },
        "total_cust_s": 2264694,
        "total_outages": 97
      }
    ],
    "date_generated": "2025-09-04T08:44:07.471Z",
    "overwritten_ca": false,
    "overwritten_etr": false,
    "page_mode": {
      "mode": "BLUESKY",
      "redirectURL": "",
      "pausePublish": false
    }
  }
}