{
  "fileTitle": "data",
  "summaryFileData": {
    "totals": [
      {
        "summaryTotalId": "total-1",
        "total_cust_a": {
          "val": 250
        },
        "total_percent_cust_a": {
          "val": 0.02
        },
        "total_percent_cust_active": {
          "val": 99.98
        },
        "total_cust_s": 2261339,
        "total_outages": 11
      }
    ],
    "date_generated": "2025-01-17T09:12:54.737Z",
    "overwritten_ca": false,
    "overwritten_etr": false,
    "page_mode": {
      "mode": "BLUESKY",
      "redirectURL": "",
      "pausePublish": false
    }
  }
}