{
  "fileTitle": "data",
  "summaryFileData": {
    "totals": [
      {
        "summaryTotalId": "total-1",
        "total_cust_a": {
          "val": 90
        },
        "total_percent_cust_a": {
          "val": 0.01
        },
        "total_percent_cust_active": {
          "val": 99.99
        },
        "total_cust_s": 2243868,
        "total_outages": 53
      }
    ],
    "date_generated": "2024-06-08T07:13:35.031Z",
    "overwritten_ca": false,
    "overwritten_etr": false,
    "page_mode": {
      "mode": "BLUESKY",
      "redirectURL": "",
      "pausePublish": false
    }
  }
}